{
    "ชอบ": 9109,
    "ดี": 7641,
    "สนุก": 3336,
    "รัก": 3321,
    "ได้ดี": 2458,
    "ชม": 1987,
    "สวย": 1812,
    "อิน": 1616,
    "น่าสนใจ": 1550,
    "ตลก": 1547,
    "ฮา": 1518,
    "ลุ้น": 1369,
    "ร้าย": 1315,
    "น่ารัก": 1208,
    "ดีกว่า": 1079,
    "โอเค": 986,
    "ยอดเยี่ยม": 922,
    "ปัญหา": 889,
    "มันส์": 820,
    "ดีมาก": 818,
    "น่ากลัว": 808,
    "เด่น": 764,
    "ดีๆ": 747,
    "ตื่นเต้น": 733,
    "ขำ": 724,
    "เบื่อ": 721,
    "ลงตัว": 703,
    "ประทับใจ": 695,
    "ธรรมดา": 685,
    "สวยงาม": 684,
    "ชัดเจน": 680,
    "สงสัย": 679,
    "งง": 675,
    "โดดเด่น": 653,
    "ติ": 648,
    "พีค": 644,
    "ผิดหวัง": 640,
    "สนใจ": 616,
    "โหด": 601,
    "สมจริง": 592,
    "สุดยอด": 572,
    "แย่": 564,
    "ไม่ดี": 555,
    "ความสนุก": 555,
    "น่าเบื่อ": 542,
    "โรแมนติก": 540,
    "ระทึก": 522,
    "อลังการ": 518,
    "พิเศษ": 517,
    "ใช้ได้": 508,
    "แปลกใหม่": 495,
    "เจ๋ง": 471,
    "จดจำ": 470,
    "เท่": 467,
    "หลอน": 455,
    "ไม่จำเป็น": 452,
    "หลุด": 444,
    "แปลก": 441,
    "หักมุม": 438,
    "ซับซ้อน": 438,
    "เศร้า": 437,
    "ไม่สน": 425,
    "เนียน": 425,
    "ฉลาด": 424,
    "น่าเสียดาย": 403,
    "เข้มข้น": 393,
    "มีความสุข": 390,
    "เยี่ยม": 387,
    "เพลินๆ": 373,
    "เวอร์": 369,
    "ดูดี": 362,
    "ไม่เข้าใจ": 356,
    "คุ้ม": 350,
    "สะใจ": 337,
    "เครียด": 336,
    "เพลิน": 332,
    "หลากหลาย": 332,
    "รุนแรง": 330,
    "คุ้มค่า": 322,
    "สวยๆ": 321,
    "ชื่นชอบ": 321,
    "พัฒนา": 318,
    "เดิมๆ": 317,
    "มีเสน่ห์": 311,
    "น่าดู": 311,
    "ดีมากๆ": 311,
    "ประสบความสำเร็จ": 302,
    "ดีนะ": 301,
    "ให้ความรู้": 298,
    "วก": 285,
    "ตกใจ": 274,
    "สยอง": 272,
    "ละเอียด": 265,
    "ชัด": 265,
    "ฟิน": 255,
    "สมเหตุสมผล": 245,
    "เหมาะสม": 243,
    "มากเกินไป": 240,
    "อย่างชัดเจน": 235,
    "เลวร้าย": 234,
    "ทำร้าย": 232,
    "งดงาม": 226,
    "กระชับ": 226,
    "แน่น": 225,
    "อึดอัด": 225,
    "ลึกลับ": 225,
    "ดีงาม": 221,
    "อ่อน": 220,
    "แปลกใจ": 219,
    "หลงรัก": 219,
    "สมบูรณ์": 214,
    "มาตรฐาน": 214,
    "งงๆ": 213,
    "เรียบง่าย": 212,
    "มันดี": 201,
    "เฟค": 197,
    "สวยมาก": 197,
    "พัง": 197,
    "สร้างสรรค์": 196,
    "มีเหตุผล": 194,
    "เป๊ะ": 192,
    "มาคุ": 192,
    "เห็นภาพ": 184,
    "ลึกซึ้ง": 184,
    "หวือหวา": 180,
    "เข้าใจง่าย": 176,
    "ไม่น่าเชื่อ": 172,
    "กลมกล่อม": 163,
    "สมบูรณ์แบบ": 161,
    "ดีขึ้น": 160,
    "เกินคาด": 153,
    "รำคาญ": 152,
    "น่ารำคาญ": 151,
    "เท่ห์": 150,
    "เชย": 150,
    "เลว": 148,
    "เซอร์ไพรส์": 146,
    "ลื่นไหล": 146,
    "น่าทึ่ง": 145,
    "เข้ากัน": 143,
    "โดนใจ": 142,
    "สอบผ่าน": 141,
    "เคลียร์": 136,
    "ทรมาน": 136,
    "ใส่ใจ": 135,
    "เรียล": 135,
    "น้ำตาไหล": 134,
    "ขนลุก": 132,
    "เพลิดเพลิน": 124,
    "ฮาๆ": 121,
    "ว้าว": 121,
    "ปลื้ม": 120,
    "เซ็ง": 119,
    "ตื่นตา": 117,
    "ซาบซึ้ง": 116,
    "เถื่อน": 113,
    "กากๆ": 113,
    "ไร้สาระ": 109,
    "หนักหน่วง": 107,
    "ตื่นตาตื่นใจ": 103,
    "มีความสำคัญ": 99,
    "คาดไม่ถึง": 99,
    "สะเทือนใจ": 98,
    "ไม่ชัด": 97,
    "เหลือเชื่อ": 96,
    "ดีจริงๆ": 96,
    "วิเศษ": 95,
    "ผ่อนคลาย": 95,
    "ติดใจ": 93,
    "มืออาชีพ": 92,
    "ตระการตา": 91,
    "เร้าใจ": 90,
    "น่าตื่นเต้น": 90,
    "ไลค์": 85,
    "อย่างสวยงาม": 82,
    "มันส์ๆ": 82,
    "ฉับไว": 82,
    "เป๊ะๆ": 81,
    "ล้มเหลว": 81,
    "โอเวอร์": 80,
    "โปร": 80,
    "พอดูได้": 80,
    "บีบคั้น": 80,
    "น่าชื่นชม": 79,
    "มหัศจรรย์": 78,
    "ปรบมือ": 78,
    "กาก": 77,
    "แหวกแนว": 75,


}